mcp_kit/__init__.py
mcp_kit/factory.py
mcp_kit/mixins.py
mcp_kit/patch_mcp.py
mcp_kit/proxy.py
mcp_kit/types.py
mcp_kit/adapters/__init__.py
mcp_kit/adapters/client_session.py
mcp_kit/adapters/langgraph.py
mcp_kit/adapters/openai.py
mcp_kit/generators/__init__.py
mcp_kit/generators/interfaces.py
mcp_kit/generators/llm.py
mcp_kit/generators/random.py
mcp_kit/prompts/__init__.py
mcp_kit/prompts/interfaces.py
mcp_kit/prompts/interpolation.py
mcp_kit/targets/__init__.py
mcp_kit/targets/interfaces.py
mcp_kit/targets/mcp.py
mcp_kit/targets/mocked.py
mcp_kit/targets/multiplex.py
mcp_kit/targets/oas.py
mcp_kit/targets/proxy.py
mcp_kit-0.2.2.dist-info/METADATA
mcp_kit-0.2.2.dist-info/WHEEL
mcp_kit-0.2.2.dist-info/RECORD
