Metadata-Version: 2.4
Name: mcp-kit
Version: 0.2.2
Summary: MCP tooling for developing and optimizing multi-agent AI systems.
Project-URL: Homepage, https://agentiqs.ai/
Project-URL: Documentation, https://docs.agentiqs.ai/mcp-kit-python/docs
Project-URL: Repository, https://github.com/agentiqs/mcp-kit-python
Project-URL: Issues, https://github.com/agentiqs/mcp-kit-python/issues
Project-URL: Changelog, https://github.com/agentiqs/mcp-kit-python/blob/main/CHANGELOG.md
Author-email: Agentiqs <support@agentiqs.ai>
Maintainer-email: Mauro <mauro@agentiqs.ai>, Guido <guido@agentiqs.ai>
License-Expression: Apache-2.0
Keywords: agent,ai,llm,mcp,mock,oas,openapi,proxy,tool
Classifier: Development Status :: 4 - Beta
Classifier: Intended Audience :: Developers
Classifier: License :: OSI Approved :: Apache Software License
Classifier: Operating System :: MacOS
Classifier: Operating System :: Microsoft :: Windows
Classifier: Operating System :: OS Independent
Classifier: Operating System :: POSIX
Classifier: Operating System :: POSIX :: Linux
Classifier: Programming Language :: Python :: 3.10
Classifier: Programming Language :: Python :: 3.11
Classifier: Programming Language :: Python :: 3.12
Classifier: Topic :: Software Development :: Libraries :: Python Modules
Classifier: Typing :: Typed
Requires-Python: <3.13,>=3.10
Requires-Dist: fastapi[standard]<1,>=0.115.12
Requires-Dist: litellm<2,>=1.72.6
Requires-Dist: mcp<1.10,>=1.9.4
Requires-Dist: omegaconf<3,>=2.3.0
Requires-Dist: openapi-core<1,>=0.19.5
Requires-Dist: openapi-mcp<1,>=0.1.0
Requires-Dist: python-dotenv<2,>=1.1.0
Requires-Dist: typing-extensions<5,>=4.14.0
Provides-Extra: langgraph
Requires-Dist: langchain-mcp-adapters==0.1.1; extra == 'langgraph'
